louisboyaval_picsou/__init__.py
louisboyaval_picsou/picsou.py
louisboyaval_picsou-0.1.0.dist-info/METADATA
louisboyaval_picsou-0.1.0.dist-info/WHEEL
louisboyaval_picsou-0.1.0.dist-info/RECORD
